mkdocsdrawioexporter/__init__.py
mkdocsdrawioexporter/exporter.py
mkdocsdrawioexporter/plugin.py
mkdocs_drawio_exporter_fork-0.9.1.dist-info/LICENSE.md
mkdocs_drawio_exporter_fork-0.9.1.dist-info/METADATA
mkdocs_drawio_exporter_fork-0.9.1.dist-info/WHEEL
mkdocs_drawio_exporter_fork-0.9.1.dist-info/entry_points.txt
mkdocs_drawio_exporter_fork-0.9.1.dist-info/top_level.txt
mkdocs_drawio_exporter_fork-0.9.1.dist-info/RECORD
