Metadata-Version: 2.1
Name: mkdocs-drawio-exporter-fork
Version: 0.9.1
Summary: Exports your Draw.io diagrams at build time for easier embedding into your documentation
Home-page: https://github.com/herberton/mkdocs-drawio-exporter
Author: Herberton Candido Souza
Author-email: herberton@gmail.com
License: MIT
Platform: UNKNOWN
License-File: LICENSE.md
Requires-Dist: mkdocs
